{"GlobalPropertiesHash":"wyKGchpzm+utCWKQWmMlos0swJpqc71MVbdTHWLoGng=","FingerprintPatternsHash":"gq3WsqcKBUGTSNle7RKKyXRIwh7M8ccEqOqYvIzoM04=","PropertyOverridesHash":"8ZRc1sGeVrPBx4lD717BgRaQekyh78QKV9SKsdt638U=","InputHashes":["RFkBxHAdmPW3WrKLSEcxhV8ZXuDTpnTuYopdAvmMpyQ=","SU1TbKe80XENWoHYlZn9siYnZSLL6TH0dBupup8eG1o=","POCCMAYgaMCKoi9fiqmxgPnir9taSECWa9qzgChKoFk=","xTUgVt5V2VhP3vVbKbqYEwK2wZ2V83IYFH4pHJYsQdg=","fjQJWlE7h5Nd\u002BiVuCOpLb705WGe3V9sPm\u002BeLKpShmBc=","JifWFKC3c7aVX2i\u002B0dnsZl6ojvHWpgAEwVHQazBzEH4=","\u002BrB1BBDciOzYtknVjtaqc2HW48CpahhidQI06giUG1U=","yBhhgZs9qCJ4xzKdiSHbgmv77xkhulVQVSzDSuGZ\u002Bw0=","FbqxUl9OxOH7bqrbL92BeU\u002BgTB5qltRCmqv/AKebXp0=","nnHyQPMPBjEupJ5Z1h1h2rOCxLw6f37hh9gC1NYKxS0=","Z5evJve/2dY/AW76Wyb6v5ALweZWhVUBC/o/2Xbi82Y=","mhmdAOMHjD9U8Xm1SHnYmCAQpPGgqjduWWqTJiN2Fa8=","b2ML6jCrye49BpIA19seCc8HptSfrnoeMaD2LXDwv6Y=","PazWrxzUhBO71WTBZ0/kPjRbI0MnG/1efbanbFbP4Oc=","yMjXqq3yvm\u002BldLTyrZIZyqXHbqR5sLuabE9yh8I4\u002B1c=","OdrlCfYzU/CdE38ldfYNi26V48bazGZtPasm1T7T\u002BOA=","PapcCyfyKk7ZvCoMnB8XnldpmvMo6zE/cVY7MvSXCxk=","C5fiO59ezyEPyQ5gox2hTxZp2W0td77uzJ2RO2EEy1o=","Q9yxDi53rIf22X2/GyE80HZ4S\u002BNKdJ6ciQOM6XK94wQ=","fOZJ0t1i8MRD6IgpxqYZH6VEEuLO/AbM0ilyf6WK07c=","jwpn8RxSwXLu3Tsc/HDe2FwMcj7kyc2YRSkEn94cDio=","tAeFTlI2xipg1V64ilerXogiBI/32DEz9WplwDrJMO0=","GPUyjTG7AZLSBGSjq8B/bCT51mKQy5pqh8\u002B9Qm986Dk="],"CachedAssets":{"RFkBxHAdmPW3WrKLSEcxhV8ZXuDTpnTuYopdAvmMpyQ=":{"Identity":"D:\\Development\\AlAfkar\\HR\\ALAFKARHR\\UI\\AlAfkarERP\\AlAfkarERP.Shared\\wwwroot\\app.css","SourceId":"AlAfkarERP.Shared","SourceType":"Discovered","ContentRoot":"D:\\Development\\AlAfkar\\HR\\ALAFKARHR\\UI\\AlAfkarERP\\AlAfkarERP.Shared\\wwwroot\\","BasePath":"_content/AlAfkarERP.Shared","RelativePath":"app#[.{fingerprint}]?.css","AssetKind":"All","AssetMode":"All","AssetRole":"Primary","AssetMergeBehavior":null,"AssetMergeSource":"","RelatedAsset":null,"AssetTraitName":null,"AssetTraitValue":null,"Fingerprint":"m7afdfk5lv","Integrity":"ciptI/Tq2bBOfaAIRhRI1Td8vVpSNyY\u002BwT7yDkkDwh8=","CopyToOutputDirectory":"Never","CopyToPublishDirectory":"PreserveNewest","OriginalItemSpec":"wwwroot\\app.css","FileLength":2465,"LastWriteTime":"2026-04-13T11:35:52.1821044+00:00"},"SU1TbKe80XENWoHYlZn9siYnZSLL6TH0dBupup8eG1o=":{"Identity":"D:\\Development\\AlAfkar\\HR\\ALAFKARHR\\UI\\AlAfkarERP\\AlAfkarERP.Shared\\wwwroot\\lib\\bootstrap\\dist\\css\\bootstrap.min.css","SourceId":"AlAfkarERP.Shared","SourceType":"Discovered","ContentRoot":"D:\\Development\\AlAfkar\\HR\\ALAFKARHR\\UI\\AlAfkarERP\\AlAfkarERP.Shared\\wwwroot\\","BasePath":"_content/AlAfkarERP.Shared","RelativePath":"lib/bootstrap/dist/css/bootstrap.min#[.{fingerprint}]?.css","AssetKind":"All","AssetMode":"All","AssetRole":"Primary","AssetMergeBehavior":null,"AssetMergeSource":"","RelatedAsset":null,"AssetTraitName":null,"AssetTraitValue":null,"Fingerprint":"08mtdlppm0","Integrity":"QHmL423\u002Bqgn8fqkPD2Hb/blzaK8A4ALJRal/4lVYPMs=","CopyToOutputDirectory":"Never","CopyToPublishDirectory":"PreserveNewest","OriginalItemSpec":"wwwroot\\lib\\bootstrap\\dist\\css\\bootstrap.min.css","FileLength":232810,"LastWriteTime":"2026-03-14T17:53:51.1039263+00:00"},"POCCMAYgaMCKoi9fiqmxgPnir9taSECWa9qzgChKoFk=":{"Identity":"D:\\Development\\AlAfkar\\HR\\ALAFKARHR\\UI\\AlAfkarERP\\AlAfkarERP.Shared\\wwwroot\\lib\\bootstrap\\dist\\css\\bootstrap.min.css.map","SourceId":"AlAfkarERP.Shared","SourceType":"Discovered","ContentRoot":"D:\\Development\\AlAfkar\\HR\\ALAFKARHR\\UI\\AlAfkarERP\\AlAfkarERP.Shared\\wwwroot\\","BasePath":"_content/AlAfkarERP.Shared","RelativePath":"lib/bootstrap/dist/css/bootstrap.min.css#[.{fingerprint}]?.map","AssetKind":"All","AssetMode":"All","AssetRole":"Primary","AssetMergeBehavior":null,"AssetMergeSource":"","RelatedAsset":null,"AssetTraitName":null,"AssetTraitValue":null,"Fingerprint":"ca434j9tb9","Integrity":"dLjmWc4YRAp7XkxEmYm7/xV1ebW\u002BYQ0LrlrrKVB8kXY=","CopyToOutputDirectory":"Never","CopyToPublishDirectory":"PreserveNewest","OriginalItemSpec":"wwwroot\\lib\\bootstrap\\dist\\css\\bootstrap.min.css.map","FileLength":589893,"LastWriteTime":"2026-03-14T17:53:51.1064644+00:00"},"xTUgVt5V2VhP3vVbKbqYEwK2wZ2V83IYFH4pHJYsQdg=":{"Identity":"D:\\Development\\AlAfkar\\HR\\ALAFKARHR\\UI\\AlAfkarERP\\AlAfkarERP.Shared\\wwwroot\\lib\\MyJs\\Charts.js","SourceId":"AlAfkarERP.Shared","SourceType":"Discovered","ContentRoot":"D:\\Development\\AlAfkar\\HR\\ALAFKARHR\\UI\\AlAfkarERP\\AlAfkarERP.Shared\\wwwroot\\","BasePath":"_content/AlAfkarERP.Shared","RelativePath":"lib/MyJs/Charts#[.{fingerprint}]?.js","AssetKind":"All","AssetMode":"All","AssetRole":"Primary","AssetMergeBehavior":null,"AssetMergeSource":"","RelatedAsset":null,"AssetTraitName":null,"AssetTraitValue":null,"Fingerprint":"oo0scvzsl7","Integrity":"eIpwRlJ4Zu1Ou7wM1o7wT9ZgmCJzR78WIwB2yAFIFng=","CopyToOutputDirectory":"Never","CopyToPublishDirectory":"PreserveNewest","OriginalItemSpec":"wwwroot\\lib\\MyJs\\Charts.js","FileLength":773,"LastWriteTime":"2026-04-12T15:48:19.1430529+00:00"},"fjQJWlE7h5Nd\u002BiVuCOpLb705WGe3V9sPm\u002BeLKpShmBc=":{"Identity":"D:\\Development\\AlAfkar\\HR\\ALAFKARHR\\UI\\AlAfkarERP\\AlAfkarERP.Shared\\wwwroot\\lib\\MyJs\\PopupMessage.js","SourceId":"AlAfkarERP.Shared","SourceType":"Discovered","ContentRoot":"D:\\Development\\AlAfkar\\HR\\ALAFKARHR\\UI\\AlAfkarERP\\AlAfkarERP.Shared\\wwwroot\\","BasePath":"_content/AlAfkarERP.Shared","RelativePath":"lib/MyJs/PopupMessage#[.{fingerprint}]?.js","AssetKind":"All","AssetMode":"All","AssetRole":"Primary","AssetMergeBehavior":null,"AssetMergeSource":"","RelatedAsset":null,"AssetTraitName":null,"AssetTraitValue":null,"Fingerprint":"gzixtfi2la","Integrity":"XFcHyR15o/drDEaD\u002BN/P1eCL2yrGc54Vc0SKhPuGCtk=","CopyToOutputDirectory":"Never","CopyToPublishDirectory":"PreserveNewest","OriginalItemSpec":"wwwroot\\lib\\MyJs\\PopupMessage.js","FileLength":802,"LastWriteTime":"2026-03-27T04:52:37.7372636+00:00"}},"CachedCopyCandidates":{}}