[
  {
    "ContainingType": "Auth.Users.Features.ChangePassword.ChangePasswordEndPoint\u002B\u003C\u003Ec",
    "Method": "\u003CAddRoutes\u003Eb__0_0",
    "RelativePath": "api/v1/auth/change-password",
    "HttpMethod": "POST",
    "IsController": false,
    "Order": 0,
    "Parameters": [
      {
        "Name": "request",
        "Type": "Auth.Users.Features.ChangePassword.ChangePasswordRequest",
        "IsRequired": true
      }
    ],
    "ReturnTypes": [
      {
        "Type": "Auth.Users.Features.ChangePassword.ChangePasswordResponse",
        "MediaTypes": [
          "application/json"
        ],
        "StatusCode": 200
      },
      {
        "Type": "Microsoft.AspNetCore.Mvc.ProblemDetails",
        "MediaTypes": [
          "application/problem\u002Bjson"
        ],
        "StatusCode": 400
      },
      {
        "Type": "Microsoft.AspNetCore.Mvc.ProblemDetails",
        "MediaTypes": [
          "application/problem\u002Bjson"
        ],
        "StatusCode": 404
      }
    ],
    "EndpointName": "ChangePassword",
    "Description": "Allows a user to change their password by providing their current password and a new password.",
    "Summary": "Change Password"
  },
  {
    "ContainingType": "Auth.Users.Features.ConfirmOTP.ConfirmOTPEndPoint\u002B\u003C\u003Ec",
    "Method": "\u003CAddRoutes\u003Eb__0_0",
    "RelativePath": "api/v1/auth/confirm-otp",
    "HttpMethod": "POST",
    "IsController": false,
    "Order": 0,
    "Parameters": [
      {
        "Name": "request",
        "Type": "Auth.Users.Features.ConfirmOTP.ConfirmOTPRequest",
        "IsRequired": true
      }
    ],
    "ReturnTypes": [
      {
        "Type": "Auth.Users.Features.ConfirmOTP.ConfirmOTPResponse",
        "MediaTypes": [
          "application/json"
        ],
        "StatusCode": 200
      },
      {
        "Type": "Microsoft.AspNetCore.Mvc.ProblemDetails",
        "MediaTypes": [
          "application/problem\u002Bjson"
        ],
        "StatusCode": 400
      },
      {
        "Type": "Microsoft.AspNetCore.Mvc.ProblemDetails",
        "MediaTypes": [
          "application/problem\u002Bjson"
        ],
        "StatusCode": 404
      }
    ],
    "EndpointName": "ConfirmOTP",
    "Description": "Confirm OTP",
    "Summary": "Confirm OTP"
  },
  {
    "ContainingType": "Auth.Users.Features.Login.LoginEndPoint\u002B\u003C\u003Ec",
    "Method": "\u003CAddRoutes\u003Eb__0_0",
    "RelativePath": "api/v1/auth/login",
    "HttpMethod": "POST",
    "IsController": false,
    "Order": 0,
    "Parameters": [
      {
        "Name": "request",
        "Type": "Auth.Users.Features.Login.LoginRequest",
        "IsRequired": true
      }
    ],
    "ReturnTypes": [
      {
        "Type": "Auth.Users.Features.Login.LoginResponse",
        "MediaTypes": [
          "application/json"
        ],
        "StatusCode": 200
      },
      {
        "Type": "Microsoft.AspNetCore.Mvc.ProblemDetails",
        "MediaTypes": [
          "application/problem\u002Bjson"
        ],
        "StatusCode": 400
      }
    ],
    "EndpointName": "Login",
    "Description": "Login",
    "Summary": "Login"
  },
  {
    "ContainingType": "Auth.Users.Features.ValidateRefreshToken.RefreshTokenEndPoint\u002B\u003C\u003Ec",
    "Method": "\u003CAddRoutes\u003Eb__0_0",
    "RelativePath": "api/v1/auth/refresh-token",
    "HttpMethod": "POST",
    "IsController": false,
    "Order": 0,
    "Parameters": [
      {
        "Name": "request",
        "Type": "Auth.Users.Features.ValidateRefreshToken.RefreshTokenRequest",
        "IsRequired": true
      }
    ],
    "ReturnTypes": [
      {
        "Type": "Auth.Users.Features.ValidateRefreshToken.RefreshTokenResponse",
        "MediaTypes": [
          "application/json"
        ],
        "StatusCode": 200
      },
      {
        "Type": "Microsoft.AspNetCore.Mvc.ProblemDetails",
        "MediaTypes": [
          "application/problem\u002Bjson"
        ],
        "StatusCode": 400
      }
    ],
    "EndpointName": "RefreshToken",
    "Description": "Refresh Token",
    "Summary": "Refresh Token"
  },
  {
    "ContainingType": "Auth.Users.Features.RegisterUser.RegisterUserEndPoint\u002B\u003C\u003Ec",
    "Method": "\u003CAddRoutes\u003Eb__0_0",
    "RelativePath": "api/v1/auth/register",
    "HttpMethod": "POST",
    "IsController": false,
    "Order": 0,
    "Parameters": [
      {
        "Name": "request",
        "Type": "Auth.Users.Features.RegisterUser.RegisterUserRequest",
        "IsRequired": true
      }
    ],
    "ReturnTypes": [
      {
        "Type": "Auth.Users.Features.RegisterUser.RegisterUserResponse",
        "MediaTypes": [
          "application/json"
        ],
        "StatusCode": 200
      },
      {
        "Type": "Microsoft.AspNetCore.Mvc.ProblemDetails",
        "MediaTypes": [
          "application/problem\u002Bjson"
        ],
        "StatusCode": 400
      }
    ],
    "EndpointName": "RegisterUser",
    "Description": "Register User",
    "Summary": "Register User"
  },
  {
    "ContainingType": "Auth.Users.Features.GenerateResetPasswordOTP.GenerateResetPasswordOTPEndPoint\u002B\u003C\u003Ec",
    "Method": "\u003CAddRoutes\u003Eb__0_0",
    "RelativePath": "api/v1/auth/reset-password",
    "HttpMethod": "POST",
    "IsController": false,
    "Order": 0,
    "Parameters": [
      {
        "Name": "request",
        "Type": "Auth.Users.Features.GenerateResetPasswordOTP.GenerateResetPasswordOTPRequest",
        "IsRequired": true
      }
    ],
    "ReturnTypes": [
      {
        "Type": "Auth.Users.Features.GenerateResetPasswordOTP.GenerateResetPasswordOTPResponse",
        "MediaTypes": [
          "application/json"
        ],
        "StatusCode": 200
      },
      {
        "Type": "Microsoft.AspNetCore.Mvc.ProblemDetails",
        "MediaTypes": [
          "application/problem\u002Bjson"
        ],
        "StatusCode": 400
      },
      {
        "Type": "Microsoft.AspNetCore.Mvc.ProblemDetails",
        "MediaTypes": [
          "application/problem\u002Bjson"
        ],
        "StatusCode": 404
      }
    ],
    "EndpointName": "GenerateResetPassword",
    "Description": "This endpoint generates a one-time password (OTP) for resetting the user\u0027s password and sends it to the user. The user can then use this OTP to reset their password.",
    "Summary": "Generates a reset password OTP and sends it to the user"
  },
  {
    "ContainingType": "Organization.Organizations.Features.Administrations.UpdateAdministration.UpdateAdministrationEndpoint\u002B\u003C\u003Ec",
    "Method": "\u003CAddRoutes\u003Eb__0_0",
    "RelativePath": "api/v1/organization/Administrations",
    "HttpMethod": "PUT",
    "IsController": false,
    "Order": 0,
    "Parameters": [
      {
        "Name": "request",
        "Type": "Organization.Organizations.Features.Administrations.UpdateAdministration.UpdateAdministrationRequest",
        "IsRequired": true
      }
    ],
    "ReturnTypes": [
      {
        "Type": "Organization.Organizations.Features.Administrations.UpdateAdministration.UpdateAdministrationResponse",
        "MediaTypes": [
          "application/json"
        ],
        "StatusCode": 200
      },
      {
        "Type": "Microsoft.AspNetCore.Mvc.ProblemDetails",
        "MediaTypes": [
          "application/problem\u002Bjson"
        ],
        "StatusCode": 400
      },
      {
        "Type": "Microsoft.AspNetCore.Mvc.ProblemDetails",
        "MediaTypes": [
          "application/problem\u002Bjson"
        ],
        "StatusCode": 401
      },
      {
        "Type": "Microsoft.AspNetCore.Mvc.ProblemDetails",
        "MediaTypes": [
          "application/problem\u002Bjson"
        ],
        "StatusCode": 404
      }
    ],
    "EndpointName": "UpdateAdministration",
    "Description": "UpdateAdministration",
    "Summary": "UpdateAdministration"
  },
  {
    "ContainingType": "Organization.Organizations.Features.Administrations.GetAdministrations.GetAdministrationsEndpoint\u002B\u003C\u003Ec",
    "Method": "\u003CAddRoutes\u003Eb__0_0",
    "RelativePath": "api/v1/organization/Administrations",
    "HttpMethod": "GET",
    "IsController": false,
    "Order": 0,
    "Parameters": [
      {
        "Name": "PageIndex",
        "Type": "System.Int32",
        "IsRequired": false
      },
      {
        "Name": "PageSize",
        "Type": "System.Int32",
        "IsRequired": false
      }
    ],
    "ReturnTypes": [
      {
        "Type": "Organization.Organizations.Features.Administrations.GetAdministrations.GetAdministrationsResponse",
        "MediaTypes": [
          "application/json"
        ],
        "StatusCode": 200
      },
      {
        "Type": "Microsoft.AspNetCore.Mvc.ProblemDetails",
        "MediaTypes": [
          "application/problem\u002Bjson"
        ],
        "StatusCode": 400
      }
    ],
    "EndpointName": "GetAdministrations",
    "Description": "GetAdministrations",
    "Summary": "GetAdministrations"
  },
  {
    "ContainingType": "Organization.Organizations.Features.Administrations.CreateAdministration.CreateAdministrationEdnpoint\u002B\u003C\u003Ec",
    "Method": "\u003CAddRoutes\u003Eb__0_0",
    "RelativePath": "api/v1/organization/Administrations",
    "HttpMethod": "POST",
    "IsController": false,
    "Order": 0,
    "Parameters": [
      {
        "Name": "request",
        "Type": "Organization.Organizations.Features.Administrations.CreateAdministration.CreateAdministrationRequest",
        "IsRequired": true
      }
    ],
    "ReturnTypes": [
      {
        "Type": "Organization.Organizations.Features.Administrations.CreateAdministration.CreateAdministrationResponse",
        "MediaTypes": [
          "application/json"
        ],
        "StatusCode": 201
      },
      {
        "Type": "Microsoft.AspNetCore.Mvc.ProblemDetails",
        "MediaTypes": [
          "application/problem\u002Bjson"
        ],
        "StatusCode": 400
      },
      {
        "Type": "Microsoft.AspNetCore.Mvc.ProblemDetails",
        "MediaTypes": [
          "application/problem\u002Bjson"
        ],
        "StatusCode": 401
      },
      {
        "Type": "Microsoft.AspNetCore.Mvc.ProblemDetails",
        "MediaTypes": [
          "application/problem\u002Bjson"
        ],
        "StatusCode": 404
      }
    ],
    "EndpointName": "CreateAdministration",
    "Description": "CreateAdministration",
    "Summary": "CreateAdministration"
  },
  {
    "ContainingType": "Organization.Organizations.Features.Administrations.GetAdministrationById.GetAdministrationByIdEndpoint\u002B\u003C\u003Ec",
    "Method": "\u003CAddRoutes\u003Eb__0_0",
    "RelativePath": "api/v1/organization/Administrations/{id:guid}",
    "HttpMethod": "GET",
    "IsController": false,
    "Order": 0,
    "Parameters": [
      {
        "Name": "id",
        "Type": "System.Guid",
        "IsRequired": true
      }
    ],
    "ReturnTypes": [
      {
        "Type": "Organization.Organizations.Features.Administrations.GetAdministrationById.GetAdministrationByIdResponse",
        "MediaTypes": [
          "application/json"
        ],
        "StatusCode": 200
      },
      {
        "Type": "Microsoft.AspNetCore.Mvc.ProblemDetails",
        "MediaTypes": [
          "application/problem\u002Bjson"
        ],
        "StatusCode": 400
      },
      {
        "Type": "Microsoft.AspNetCore.Mvc.ProblemDetails",
        "MediaTypes": [
          "application/problem\u002Bjson"
        ],
        "StatusCode": 404
      }
    ],
    "EndpointName": "GetAdministrationById",
    "Description": "GetAdministrationById",
    "Summary": "GetAdministrationById"
  },
  {
    "ContainingType": "Organization.Organizations.Features.Administrations.DeleteAdministration.DeleteAdministrationEndpoint\u002B\u003C\u003Ec",
    "Method": "\u003CAddRoutes\u003Eb__0_0",
    "RelativePath": "api/v1/organization/Administrations/{id:guid}",
    "HttpMethod": "DELETE",
    "IsController": false,
    "Order": 0,
    "Parameters": [
      {
        "Name": "id",
        "Type": "System.Guid",
        "IsRequired": true
      }
    ],
    "ReturnTypes": [
      {
        "Type": "Organization.Organizations.Features.Administrations.DeleteAdministration.DeleteAdministrationResponse",
        "MediaTypes": [
          "application/json"
        ],
        "StatusCode": 200
      },
      {
        "Type": "Microsoft.AspNetCore.Mvc.ProblemDetails",
        "MediaTypes": [
          "application/problem\u002Bjson"
        ],
        "StatusCode": 400
      },
      {
        "Type": "Microsoft.AspNetCore.Mvc.ProblemDetails",
        "MediaTypes": [
          "application/problem\u002Bjson"
        ],
        "StatusCode": 401
      },
      {
        "Type": "Microsoft.AspNetCore.Mvc.ProblemDetails",
        "MediaTypes": [
          "application/problem\u002Bjson"
        ],
        "StatusCode": 404
      }
    ],
    "EndpointName": "DeleteAdministration",
    "Description": "DeleteAdministration",
    "Summary": "DeleteAdministration"
  },
  {
    "ContainingType": "Organization.Organizations.Features.Branches.UpdateBranch.UpdateBranchEndpoint\u002B\u003C\u003Ec",
    "Method": "\u003CAddRoutes\u003Eb__0_0",
    "RelativePath": "api/v1/organization/Branches",
    "HttpMethod": "PUT",
    "IsController": false,
    "Order": 0,
    "Parameters": [
      {
        "Name": "request",
        "Type": "Organization.Organizations.Features.Branches.UpdateBranch.UpdateBranchRequest",
        "IsRequired": true
      }
    ],
    "ReturnTypes": [
      {
        "Type": "Organization.Organizations.Features.Branches.UpdateBranch.UpdateBranchResponse",
        "MediaTypes": [
          "application/json"
        ],
        "StatusCode": 200
      },
      {
        "Type": "Microsoft.AspNetCore.Mvc.ProblemDetails",
        "MediaTypes": [
          "application/problem\u002Bjson"
        ],
        "StatusCode": 400
      },
      {
        "Type": "Microsoft.AspNetCore.Mvc.ProblemDetails",
        "MediaTypes": [
          "application/problem\u002Bjson"
        ],
        "StatusCode": 401
      },
      {
        "Type": "Microsoft.AspNetCore.Mvc.ProblemDetails",
        "MediaTypes": [
          "application/problem\u002Bjson"
        ],
        "StatusCode": 404
      }
    ],
    "EndpointName": "UpdateBranch",
    "Description": "UpdateBranch",
    "Summary": "UpdateBranch"
  },
  {
    "ContainingType": "Organization.Organizations.Features.Branches.GetBranches.GetBranchesEndpoint\u002B\u003C\u003Ec",
    "Method": "\u003CAddRoutes\u003Eb__0_0",
    "RelativePath": "api/v1/organization/Branches",
    "HttpMethod": "GET",
    "IsController": false,
    "Order": 0,
    "Parameters": [
      {
        "Name": "PageIndex",
        "Type": "System.Int32",
        "IsRequired": false
      },
      {
        "Name": "PageSize",
        "Type": "System.Int32",
        "IsRequired": false
      }
    ],
    "ReturnTypes": [
      {
        "Type": "Organization.Organizations.Features.Branches.GetBranches.GetBranchesResponse",
        "MediaTypes": [
          "application/json"
        ],
        "StatusCode": 200
      },
      {
        "Type": "Microsoft.AspNetCore.Mvc.ProblemDetails",
        "MediaTypes": [
          "application/problem\u002Bjson"
        ],
        "StatusCode": 400
      }
    ],
    "EndpointName": "GetBranches",
    "Description": "GetBranches",
    "Summary": "GetBranches"
  },
  {
    "ContainingType": "Organization.Organizations.Features.Branches.CreateBranch.CreateBranchEndpoint\u002B\u003C\u003Ec",
    "Method": "\u003CAddRoutes\u003Eb__0_0",
    "RelativePath": "api/v1/organization/Branches",
    "HttpMethod": "POST",
    "IsController": false,
    "Order": 0,
    "Parameters": [
      {
        "Name": "request",
        "Type": "Organization.Organizations.Features.Branches.CreateBranch.CreateBranchRequest",
        "IsRequired": true
      }
    ],
    "ReturnTypes": [
      {
        "Type": "Organization.Organizations.Features.Branches.CreateBranch.CreateBranchResponse",
        "MediaTypes": [
          "application/json"
        ],
        "StatusCode": 201
      },
      {
        "Type": "Microsoft.AspNetCore.Mvc.ProblemDetails",
        "MediaTypes": [
          "application/problem\u002Bjson"
        ],
        "StatusCode": 400
      },
      {
        "Type": "Microsoft.AspNetCore.Mvc.ProblemDetails",
        "MediaTypes": [
          "application/problem\u002Bjson"
        ],
        "StatusCode": 401
      },
      {
        "Type": "Microsoft.AspNetCore.Mvc.ProblemDetails",
        "MediaTypes": [
          "application/problem\u002Bjson"
        ],
        "StatusCode": 404
      }
    ],
    "EndpointName": "CreateBranch",
    "Description": "CreateBranch",
    "Summary": "CreateBranch"
  },
  {
    "ContainingType": "Organization.Organizations.Features.Branches.GetBranchById.GetBranchByIdEndpoint\u002B\u003C\u003Ec",
    "Method": "\u003CAddRoutes\u003Eb__0_0",
    "RelativePath": "api/v1/organization/Branches/{id:guid}",
    "HttpMethod": "GET",
    "IsController": false,
    "Order": 0,
    "Parameters": [
      {
        "Name": "id",
        "Type": "System.Guid",
        "IsRequired": true
      }
    ],
    "ReturnTypes": [
      {
        "Type": "Organization.Organizations.Features.Branches.GetBranchById.GetBranchByIdResponse",
        "MediaTypes": [
          "application/json"
        ],
        "StatusCode": 200
      },
      {
        "Type": "Microsoft.AspNetCore.Mvc.ProblemDetails",
        "MediaTypes": [
          "application/problem\u002Bjson"
        ],
        "StatusCode": 400
      },
      {
        "Type": "Microsoft.AspNetCore.Mvc.ProblemDetails",
        "MediaTypes": [
          "application/problem\u002Bjson"
        ],
        "StatusCode": 404
      }
    ],
    "EndpointName": "GetBranchById",
    "Description": "GetBranchById",
    "Summary": "GetBranchById"
  },
  {
    "ContainingType": "Organization.Organizations.Features.Branches.DeleteBranch.DeleteBranchEndpoint\u002B\u003C\u003Ec",
    "Method": "\u003CAddRoutes\u003Eb__0_0",
    "RelativePath": "api/v1/organization/Branches/{id:guid}",
    "HttpMethod": "DELETE",
    "IsController": false,
    "Order": 0,
    "Parameters": [
      {
        "Name": "id",
        "Type": "System.Guid",
        "IsRequired": true
      }
    ],
    "ReturnTypes": [
      {
        "Type": "Organization.Organizations.Features.Branches.DeleteBranch.DeleteBranchResponse",
        "MediaTypes": [
          "application/json"
        ],
        "StatusCode": 200
      },
      {
        "Type": "Microsoft.AspNetCore.Mvc.ProblemDetails",
        "MediaTypes": [
          "application/problem\u002Bjson"
        ],
        "StatusCode": 400
      },
      {
        "Type": "Microsoft.AspNetCore.Mvc.ProblemDetails",
        "MediaTypes": [
          "application/problem\u002Bjson"
        ],
        "StatusCode": 404
      },
      {
        "Type": "Microsoft.AspNetCore.Mvc.ProblemDetails",
        "MediaTypes": [
          "application/problem\u002Bjson"
        ],
        "StatusCode": 401
      }
    ],
    "EndpointName": "DeleteBranch",
    "Description": "DeleteBranch",
    "Summary": "DeleteBranch"
  },
  {
    "ContainingType": "Organization.Organizations.Features.Branches.GetByCompanyId.GetByCompanyIdEndpoint\u002B\u003C\u003Ec",
    "Method": "\u003CAddRoutes\u003Eb__0_0",
    "RelativePath": "api/v1/organization/Branches/GetByCompanyId/{companyId}",
    "HttpMethod": "GET",
    "IsController": false,
    "Order": 0,
    "Parameters": [
      {
        "Name": "companyId",
        "Type": "System.Guid",
        "IsRequired": true
      }
    ],
    "ReturnTypes": [
      {
        "Type": "Organization.Organizations.Features.Branches.GetByCompanyId.GetByCompanyIdResponse",
        "MediaTypes": [
          "application/json"
        ],
        "StatusCode": 200
      },
      {
        "Type": "Microsoft.AspNetCore.Mvc.ProblemDetails",
        "MediaTypes": [
          "application/problem\u002Bjson"
        ],
        "StatusCode": 400
      }
    ],
    "EndpointName": "GetByCompanyId",
    "Description": "GetByCompanyId",
    "Summary": "GetByCompanyId"
  },
  {
    "ContainingType": "Organization.Organizations.Features.Companies.UpdateCompany.UpdateCompanyEndpoint\u002B\u003C\u003Ec",
    "Method": "\u003CAddRoutes\u003Eb__0_0",
    "RelativePath": "api/v1/organization/Companies",
    "HttpMethod": "PUT",
    "IsController": false,
    "Order": 0,
    "Parameters": [
      {
        "Name": "request",
        "Type": "Organization.Organizations.Features.Companies.UpdateCompany.UpdateCompanyRequest",
        "IsRequired": true
      }
    ],
    "ReturnTypes": [
      {
        "Type": "Organization.Organizations.Features.Companies.UpdateCompany.UpdateCompanyResponse",
        "MediaTypes": [
          "application/json"
        ],
        "StatusCode": 200
      },
      {
        "Type": "Microsoft.AspNetCore.Mvc.ProblemDetails",
        "MediaTypes": [
          "application/problem\u002Bjson"
        ],
        "StatusCode": 400
      },
      {
        "Type": "Microsoft.AspNetCore.Mvc.ProblemDetails",
        "MediaTypes": [
          "application/problem\u002Bjson"
        ],
        "StatusCode": 401
      },
      {
        "Type": "Microsoft.AspNetCore.Mvc.ProblemDetails",
        "MediaTypes": [
          "application/problem\u002Bjson"
        ],
        "StatusCode": 404
      }
    ],
    "EndpointName": "UpdateCompany",
    "Description": "UpdateCompany",
    "Summary": "UpdateCompany"
  },
  {
    "ContainingType": "Organization.Organizations.Features.Companies.GetCompanies.GetCompaniesEndpoint\u002B\u003C\u003Ec",
    "Method": "\u003CAddRoutes\u003Eb__0_0",
    "RelativePath": "api/v1/organization/Companies",
    "HttpMethod": "GET",
    "IsController": false,
    "Order": 0,
    "Parameters": [
      {
        "Name": "PageIndex",
        "Type": "System.Int32",
        "IsRequired": false
      },
      {
        "Name": "PageSize",
        "Type": "System.Int32",
        "IsRequired": false
      }
    ],
    "ReturnTypes": [
      {
        "Type": "Organization.Organizations.Features.Companies.GetCompanies.GetCompaniesResponse",
        "MediaTypes": [
          "application/json"
        ],
        "StatusCode": 200
      },
      {
        "Type": "Microsoft.AspNetCore.Mvc.ProblemDetails",
        "MediaTypes": [
          "application/problem\u002Bjson"
        ],
        "StatusCode": 400
      }
    ],
    "EndpointName": "GetCompanies",
    "Description": "GetCompanies",
    "Summary": "GetCompanies"
  },
  {
    "ContainingType": "Organization.Organizations.Features.Companies.CreateCompany.CreateCompanyEndpoint\u002B\u003C\u003Ec",
    "Method": "\u003CAddRoutes\u003Eb__0_0",
    "RelativePath": "api/v1/organization/Companies",
    "HttpMethod": "POST",
    "IsController": false,
    "Order": 0,
    "Parameters": [
      {
        "Name": "request",
        "Type": "Organization.Organizations.Features.Companies.CreateCompany.CreateCompanyRequest",
        "IsRequired": true
      }
    ],
    "ReturnTypes": [
      {
        "Type": "Organization.Organizations.Features.Companies.CreateCompany.CreateCompanyResponse",
        "MediaTypes": [
          "application/json"
        ],
        "StatusCode": 201
      },
      {
        "Type": "Microsoft.AspNetCore.Mvc.ProblemDetails",
        "MediaTypes": [
          "application/problem\u002Bjson"
        ],
        "StatusCode": 400
      },
      {
        "Type": "Microsoft.AspNetCore.Mvc.ProblemDetails",
        "MediaTypes": [
          "application/problem\u002Bjson"
        ],
        "StatusCode": 401
      }
    ],
    "EndpointName": "CreateCompany",
    "Description": "CreateCompany",
    "Summary": "CreateCompany"
  },
  {
    "ContainingType": "Organization.Organizations.Features.Companies.DeleteCompany.DeleteCompanyEndpoint\u002B\u003C\u003Ec",
    "Method": "\u003CAddRoutes\u003Eb__0_0",
    "RelativePath": "api/v1/organization/Companies{id}",
    "HttpMethod": "DELETE",
    "IsController": false,
    "Order": 0,
    "Parameters": [
      {
        "Name": "id",
        "Type": "System.Guid",
        "IsRequired": true
      }
    ],
    "ReturnTypes": [
      {
        "Type": "Organization.Organizations.Features.Companies.DeleteCompany.DeleteCompanyResponse",
        "MediaTypes": [
          "application/json"
        ],
        "StatusCode": 200
      },
      {
        "Type": "Microsoft.AspNetCore.Mvc.ProblemDetails",
        "MediaTypes": [
          "application/problem\u002Bjson"
        ],
        "StatusCode": 400
      },
      {
        "Type": "Microsoft.AspNetCore.Mvc.ProblemDetails",
        "MediaTypes": [
          "application/problem\u002Bjson"
        ],
        "StatusCode": 401
      },
      {
        "Type": "Microsoft.AspNetCore.Mvc.ProblemDetails",
        "MediaTypes": [
          "application/problem\u002Bjson"
        ],
        "StatusCode": 404
      }
    ],
    "EndpointName": "DeleteCompany",
    "Description": "DeleteCompany",
    "Summary": "DeleteCompany"
  },
  {
    "ContainingType": "Organization.Organizations.Features.Companies.GetCompanyById.GetCompanyByIdEndpoint\u002B\u003C\u003Ec",
    "Method": "\u003CAddRoutes\u003Eb__0_0",
    "RelativePath": "api/v1/organization/Companies/{id}",
    "HttpMethod": "GET",
    "IsController": false,
    "Order": 0,
    "Parameters": [
      {
        "Name": "id",
        "Type": "System.Guid",
        "IsRequired": true
      }
    ],
    "ReturnTypes": [
      {
        "Type": "Organization.Organizations.Features.Companies.GetCompanyById.GetCompanyByIdResponse",
        "MediaTypes": [
          "application/json"
        ],
        "StatusCode": 200
      },
      {
        "Type": "Microsoft.AspNetCore.Mvc.ProblemDetails",
        "MediaTypes": [
          "application/problem\u002Bjson"
        ],
        "StatusCode": 400
      },
      {
        "Type": "Microsoft.AspNetCore.Mvc.ProblemDetails",
        "MediaTypes": [
          "application/problem\u002Bjson"
        ],
        "StatusCode": 404
      }
    ],
    "EndpointName": "GetCompanyById",
    "Description": "GetCompanyById",
    "Summary": "GetCompanyById"
  },
  {
    "ContainingType": "Organization.Organizations.Features.Departments.UpdateDepartment.UpdateDepartmentEndpoint\u002B\u003C\u003Ec",
    "Method": "\u003CAddRoutes\u003Eb__0_0",
    "RelativePath": "api/v1/organization/Departments",
    "HttpMethod": "PUT",
    "IsController": false,
    "Order": 0,
    "Parameters": [
      {
        "Name": "request",
        "Type": "Organization.Organizations.Features.Departments.UpdateDepartment.UpdateDepartmentRequest",
        "IsRequired": true
      }
    ],
    "ReturnTypes": [
      {
        "Type": "Organization.Organizations.Features.Departments.UpdateDepartment.UpdateDepartmentResponse",
        "MediaTypes": [
          "application/json"
        ],
        "StatusCode": 200
      },
      {
        "Type": "Microsoft.AspNetCore.Mvc.ProblemDetails",
        "MediaTypes": [
          "application/problem\u002Bjson"
        ],
        "StatusCode": 400
      },
      {
        "Type": "Microsoft.AspNetCore.Mvc.ProblemDetails",
        "MediaTypes": [
          "application/problem\u002Bjson"
        ],
        "StatusCode": 404
      }
    ],
    "EndpointName": "UpdateDepartment",
    "Description": "UpdateDepartment",
    "Summary": "UpdateDepartment"
  },
  {
    "ContainingType": "Organization.Organizations.Features.Departments.GetDepartments.GetDepartmentsEndpoint\u002B\u003C\u003Ec",
    "Method": "\u003CAddRoutes\u003Eb__0_0",
    "RelativePath": "api/v1/organization/Departments",
    "HttpMethod": "GET",
    "IsController": false,
    "Order": 0,
    "Parameters": [
      {
        "Name": "PageIndex",
        "Type": "System.Int32",
        "IsRequired": false
      },
      {
        "Name": "PageSize",
        "Type": "System.Int32",
        "IsRequired": false
      }
    ],
    "ReturnTypes": [
      {
        "Type": "Organization.Organizations.Features.Departments.GetDepartments.GetDepartmentsResponse",
        "MediaTypes": [
          "application/json"
        ],
        "StatusCode": 200
      },
      {
        "Type": "Microsoft.AspNetCore.Mvc.ProblemDetails",
        "MediaTypes": [
          "application/problem\u002Bjson"
        ],
        "StatusCode": 400
      }
    ],
    "EndpointName": "GetDepartments",
    "Description": "GetDepartments",
    "Summary": "GetDepartments"
  },
  {
    "ContainingType": "Organization.Organizations.Features.Departments.CreateDepartment.CreateDepartmentEndpoint\u002B\u003C\u003Ec",
    "Method": "\u003CAddRoutes\u003Eb__0_0",
    "RelativePath": "api/v1/organization/Departments",
    "HttpMethod": "POST",
    "IsController": false,
    "Order": 0,
    "Parameters": [
      {
        "Name": "request",
        "Type": "Organization.Organizations.Features.Departments.CreateDepartment.CreateDepartmentRequest",
        "IsRequired": true
      }
    ],
    "ReturnTypes": [
      {
        "Type": "Organization.Organizations.Features.Departments.CreateDepartment.CreateDepartmentResponse",
        "MediaTypes": [
          "application/json"
        ],
        "StatusCode": 201
      },
      {
        "Type": "Microsoft.AspNetCore.Mvc.ProblemDetails",
        "MediaTypes": [
          "application/problem\u002Bjson"
        ],
        "StatusCode": 400
      },
      {
        "Type": "Microsoft.AspNetCore.Mvc.ProblemDetails",
        "MediaTypes": [
          "application/problem\u002Bjson"
        ],
        "StatusCode": 401
      },
      {
        "Type": "Microsoft.AspNetCore.Mvc.ProblemDetails",
        "MediaTypes": [
          "application/problem\u002Bjson"
        ],
        "StatusCode": 404
      }
    ],
    "EndpointName": "CreateDepartment",
    "Description": "CreateDepartment",
    "Summary": "CreateDepartment"
  },
  {
    "ContainingType": "Organization.Organizations.Features.Departments.GetDepartmentById.GetDepartmentByIdEndpoint\u002B\u003C\u003Ec",
    "Method": "\u003CAddRoutes\u003Eb__0_0",
    "RelativePath": "api/v1/organization/Departments/{id}",
    "HttpMethod": "GET",
    "IsController": false,
    "Order": 0,
    "Parameters": [
      {
        "Name": "id",
        "Type": "System.Guid",
        "IsRequired": true
      }
    ],
    "ReturnTypes": [
      {
        "Type": "Organization.Organizations.Features.Departments.GetDepartmentById.GetDepartmentByIdResponse",
        "MediaTypes": [
          "application/json"
        ],
        "StatusCode": 200
      },
      {
        "Type": "Microsoft.AspNetCore.Mvc.ProblemDetails",
        "MediaTypes": [
          "application/problem\u002Bjson"
        ],
        "StatusCode": 400
      },
      {
        "Type": "Microsoft.AspNetCore.Mvc.ProblemDetails",
        "MediaTypes": [
          "application/problem\u002Bjson"
        ],
        "StatusCode": 404
      }
    ],
    "EndpointName": "GetDepartmentById",
    "Description": "GetDepartmentById",
    "Summary": "GetDepartmentById"
  },
  {
    "ContainingType": "Organization.Organizations.Features.Departments.DeleteDepartment.DeleteDepartmentEndpoint\u002B\u003C\u003Ec",
    "Method": "\u003CAddRoutes\u003Eb__0_0",
    "RelativePath": "api/v1/organization/Departments/{id}",
    "HttpMethod": "DELETE",
    "IsController": false,
    "Order": 0,
    "Parameters": [
      {
        "Name": "id",
        "Type": "System.Guid",
        "IsRequired": true
      }
    ],
    "ReturnTypes": [
      {
        "Type": "Organization.Organizations.Features.Departments.DeleteDepartment.DeleteDepartmentResponse",
        "MediaTypes": [
          "application/json"
        ],
        "StatusCode": 200
      },
      {
        "Type": "Microsoft.AspNetCore.Mvc.ProblemDetails",
        "MediaTypes": [
          "application/problem\u002Bjson"
        ],
        "StatusCode": 400
      },
      {
        "Type": "Microsoft.AspNetCore.Mvc.ProblemDetails",
        "MediaTypes": [
          "application/problem\u002Bjson"
        ],
        "StatusCode": 401
      },
      {
        "Type": "Microsoft.AspNetCore.Mvc.ProblemDetails",
        "MediaTypes": [
          "application/problem\u002Bjson"
        ],
        "StatusCode": 404
      }
    ],
    "EndpointName": "DeleteDepartment",
    "Description": "DeleteDepartment",
    "Summary": "DeleteDepartment"
  },
  {
    "ContainingType": "Organization.Organizations.Features.Departments.GetDepartmentsByAdministrationId.GetDepartmentsByAdministrationIdEndpoint\u002B\u003C\u003Ec",
    "Method": "\u003CAddRoutes\u003Eb__0_0",
    "RelativePath": "api/v1/organization/DepartmentsgetByAdministrationId/{administrationId}",
    "HttpMethod": "GET",
    "IsController": false,
    "Order": 0,
    "Parameters": [
      {
        "Name": "adminstrationId",
        "Type": "System.Guid",
        "IsRequired": true
      }
    ],
    "ReturnTypes": [
      {
        "Type": "Organization.Organizations.Features.Departments.GetDepartmentsByAdministrationId.GetDepartmentsByAdministrationIdResponse",
        "MediaTypes": [
          "application/json"
        ],
        "StatusCode": 200
      },
      {
        "Type": "Microsoft.AspNetCore.Mvc.ProblemDetails",
        "MediaTypes": [
          "application/problem\u002Bjson"
        ],
        "StatusCode": 400
      }
    ],
    "EndpointName": "GetDepartmentsByAdministrationId",
    "Description": "GetDepartmentsByAdministrationId",
    "Summary": "GetDepartmentsByAdministrationId"
  }
]